{
  "session_id": "20260130_165734",
  "agent_id": 12,
  "start_time": "2026-01-30T16:57:38.007526",
  "end_time": "2026-01-30T17:04:44.378494",
  "duration_seconds": 426.370968,
  "initial_capital": 10000.0,
  "final_portfolio_value": 9832.803681676522,
  "final_buyhold_value": 9958.285401839992,
  "total_return_pct": -1.6719631832347814,
  "buyhold_return_pct": -0.41714598160007554,
  "outperformance_pct": -1.2600735478045744,
  "total_steps": 5,
  "total_trades": 19,
  "winning_trades": 0,
  "losing_trades": 0,
  "win_rate_pct": 0.0,
  "final_cash": 3708.929881322379,
  "final_positions": {
    "BTC/FDUSD": 0.029292402540716946,
    "ETH/FDUSD": 0.3385441955250219,
    "BNB/FDUSD": 0.5774555908416096,
    "ADA/FDUSD": 0.0,
    "XRP/FDUSD": 346.93909023785073,
    "DOGE/FDUSD": 3041.4519881751344,
    "DOT/FDUSD": 432.57583258108855,
    "LTC/FDUSD": 2.18310628796032,
    "LINK/FDUSD": 42.61229194025857
  },
  "fee_rate": 0.001,
  "slippage": 0.0005
}