{
  "session_id": "20260131_145122",
  "agent_id": 21,
  "start_time": "2026-01-31T14:51:24.936860",
  "end_time": "2026-01-31T17:48:00.322285",
  "duration_seconds": 10595.385425,
  "initial_capital": 10000.0,
  "final_portfolio_value": 9246.560227215377,
  "final_buyhold_value": 9604.256138758881,
  "total_return_pct": -7.5343977278462315,
  "buyhold_return_pct": -3.9574386124111904,
  "outperformance_pct": -3.724347897178504,
  "total_steps": 136,
  "total_trades": 111,
  "winning_trades": 13,
  "losing_trades": 17,
  "win_rate_pct": 11.711711711711711,
  "final_cash": 2972.562137998135,
  "final_positions": {
    "BTC/FDUSD": 0.0,
    "ETH/FDUSD": 0.0612959392908585,
    "BNB/FDUSD": 0.01969854344262755,
    "ADA/FDUSD": 412.5957670645197,
    "XRP/FDUSD": 173.2698652416357,
    "DOGE/FDUSD": 706.7318027930658,
    "DOT/FDUSD": 1786.8669907732074,
    "LTC/FDUSD": 50.70033512936697,
    "LINK/FDUSD": 0.6354018668557198
  },
  "fee_rate": 0.001,
  "slippage": 0.0005
}