{
  "session_id": "20260131_145122",
  "agent_id": 21,
  "start_time": "2026-01-31T14:51:24.936860",
  "end_time": "2026-01-31T16:34:17.273756",
  "duration_seconds": 6172.336896,
  "initial_capital": 10000.0,
  "final_portfolio_value": 9635.483968961944,
  "final_buyhold_value": 10025.969923153025,
  "total_return_pct": -3.6451603103805574,
  "buyhold_return_pct": 0.25969923153024155,
  "outperformance_pct": -3.8947449192853645,
  "total_steps": 79,
  "total_trades": 76,
  "winning_trades": 12,
  "losing_trades": 12,
  "win_rate_pct": 15.789473684210526,
  "final_cash": 4570.862638790268,
  "final_positions": {
    "BTC/FDUSD": 0.0,
    "ETH/FDUSD": 0.0612959392908585,
    "BNB/FDUSD": 0.01969854344262755,
    "ADA/FDUSD": 3.671600240218658e-05,
    "XRP/FDUSD": 173.2698652416357,
    "DOGE/FDUSD": 706.7318027930658,
    "DOT/FDUSD": 925.6019016158567,
    "LTC/FDUSD": 50.57225528012256,
    "LINK/FDUSD": 0.05755058568464977
  },
  "fee_rate": 0.001,
  "slippage": 0.0005
}