{
  "session_id": "20260130_165734",
  "agent_id": 12,
  "start_time": "2026-01-30T16:57:38.007526",
  "end_time": "2026-01-30T17:00:45.782241",
  "duration_seconds": 187.774715,
  "initial_capital": 10000.0,
  "final_portfolio_value": 9911.814106803482,
  "final_buyhold_value": 9999.191429728317,
  "total_return_pct": -0.8818589319651848,
  "buyhold_return_pct": -0.008085702716831289,
  "outperformance_pct": -0.8738438856671471,
  "total_steps": 2,
  "total_trades": 8,
  "winning_trades": 0,
  "losing_trades": 0,
  "win_rate_pct": 0.0,
  "final_cash": 6011.820155480611,
  "final_positions": {
    "BTC/FDUSD": 0.018613095126121904,
    "ETH/FDUSD": 0.15259681720689758,
    "BNB/FDUSD": 0.3744317053735165,
    "ADA/FDUSD": 0.0,
    "XRP/FDUSD": 346.93909023785073,
    "DOGE/FDUSD": 3041.4519881751344,
    "DOT/FDUSD": 238.6361772091568,
    "LTC/FDUSD": 0.0,
    "LINK/FDUSD": 23.017055655296232
  },
  "fee_rate": 0.001,
  "slippage": 0.0005
}